.gitignore
LICENSE
README.md
getsonde.sh
setup.py
sonde2kml.py
misc/20230116-230717_U2450615_RS41_404000_sonde.kmz
misc/20230117-112338_U2450614_RS41_404001_sonde.kmz
misc/20230117-230557_U2450622_RS41_404001_sonde.kmz
misc/20230118-110354_U2540033_RS41_404001_sonde.kmz
misc/20230118-230610_U2540023_RS41_404001_sonde.kmz
misc/20230119-110735_U2450623_RS41_404001_sonde.kmz
misc/GoogleEarth-Sonde.png
misc/balloon.png
misc/marker.png
sonde2kml.egg-info/PKG-INFO
sonde2kml.egg-info/SOURCES.txt
sonde2kml.egg-info/dependency_links.txt
sonde2kml.egg-info/entry_points.txt
sonde2kml.egg-info/requires.txt
sonde2kml.egg-info/top_level.txt