Metadata-Version: 2.1
Name: sonde2kml
Version: 0.0.7
Summary: Radiosondes KML files
Home-page: https://github.com/0x9900/sonde2kml/
Author: Fred C. (W6BSD)
Author-email: w6bsd@bsdworld.org
License: BSD
Classifier: Development Status :: 3 - Alpha
Classifier: Intended Audience :: Telecommunications Industry
Classifier: License :: OSI Approved :: BSD License
Classifier: Operating System :: OS Independent
Classifier: Programming Language :: Python
Classifier: Programming Language :: Python :: 3.5
Classifier: Topic :: Communications :: Ham Radio
License-File: LICENSE
